pulumi_elasticstack
