Metadata-Version: 2.1
Name: pulumi-elasticstack
Version: 0.0.9
Summary: A Pulumi package for creating and managing elasticstack cloud resources.
Home-page: https://www.pulumi.com
License: Apache-2.0
Project-URL: Repository, https://github.com/pulumi/pulumi-elasticstack
Keywords: pulumi elasticstack category/cloud
Platform: UNKNOWN
